.gitignore
.travis.yml
INSTALL.md
LICENSE
MANIFEST.in
README.md
UNIMPLEMENTED
dev-requirements.txt
requirements.txt
setup.py
cudd-3.0.0/Doxyfile.in
cudd-3.0.0/LICENSE
cudd-3.0.0/Makefile.am
cudd-3.0.0/Makefile.in
cudd-3.0.0/README
cudd-3.0.0/RELEASE.NOTES
cudd-3.0.0/aclocal.m4
cudd-3.0.0/config.h.in
cudd-3.0.0/configure
cudd-3.0.0/configure.ac
cudd-3.0.0/groups.dox
cudd-3.0.0/build-aux/ar-lib
cudd-3.0.0/build-aux/compile
cudd-3.0.0/build-aux/config.guess
cudd-3.0.0/build-aux/config.sub
cudd-3.0.0/build-aux/depcomp
cudd-3.0.0/build-aux/install-sh
cudd-3.0.0/build-aux/ltmain.sh
cudd-3.0.0/build-aux/missing
cudd-3.0.0/build-aux/tap-driver.sh
cudd-3.0.0/cplusplus/Included.am
cudd-3.0.0/cplusplus/cuddObj.cc
cudd-3.0.0/cplusplus/cuddObj.hh
cudd-3.0.0/cplusplus/multi.out
cudd-3.0.0/cplusplus/test.out
cudd-3.0.0/cplusplus/test_obj.test.in
cudd-3.0.0/cplusplus/testmulti.cc
cudd-3.0.0/cplusplus/testobj.cc
cudd-3.0.0/cudd/Included.am
cudd-3.0.0/cudd/cudd.h
cudd-3.0.0/cudd/cuddAPI.c
cudd-3.0.0/cudd/cuddAddAbs.c
cudd-3.0.0/cudd/cuddAddApply.c
cudd-3.0.0/cudd/cuddAddFind.c
cudd-3.0.0/cudd/cuddAddInv.c
cudd-3.0.0/cudd/cuddAddIte.c
cudd-3.0.0/cudd/cuddAddNeg.c
cudd-3.0.0/cudd/cuddAddWalsh.c
cudd-3.0.0/cudd/cuddAndAbs.c
cudd-3.0.0/cudd/cuddAnneal.c
cudd-3.0.0/cudd/cuddApa.c
cudd-3.0.0/cudd/cuddApprox.c
cudd-3.0.0/cudd/cuddBddAbs.c
cudd-3.0.0/cudd/cuddBddCorr.c
cudd-3.0.0/cudd/cuddBddIte.c
cudd-3.0.0/cudd/cuddBridge.c
cudd-3.0.0/cudd/cuddCache.c
cudd-3.0.0/cudd/cuddCheck.c
cudd-3.0.0/cudd/cuddClip.c
cudd-3.0.0/cudd/cuddCof.c
cudd-3.0.0/cudd/cuddCompose.c
cudd-3.0.0/cudd/cuddDecomp.c
cudd-3.0.0/cudd/cuddEssent.c
cudd-3.0.0/cudd/cuddExact.c
cudd-3.0.0/cudd/cuddExport.c
cudd-3.0.0/cudd/cuddGenCof.c
cudd-3.0.0/cudd/cuddGenetic.c
cudd-3.0.0/cudd/cuddGroup.c
cudd-3.0.0/cudd/cuddHarwell.c
cudd-3.0.0/cudd/cuddInit.c
cudd-3.0.0/cudd/cuddInt.h
cudd-3.0.0/cudd/cuddInteract.c
cudd-3.0.0/cudd/cuddLCache.c
cudd-3.0.0/cudd/cuddLevelQ.c
cudd-3.0.0/cudd/cuddLinear.c
cudd-3.0.0/cudd/cuddLiteral.c
pycudd.egg-info/PKG-INFO
pycudd.egg-info/SOURCES.txt
pycudd.egg-info/dependency_links.txt
pycudd.egg-info/top_level.txt
