Metadata-Version: 1.2
Name: pycudd
Version: 1.1.0
Summary: PyCudd
Home-page: https://github.com/pycudd/pycudd
Author: PyCUDD Community
Author-email: noreply@github.com
Maintainer: Alexander Feldman
Maintainer-email: alex@llama.gs
License: GPLv3
Platform: UNKNOWN
Classifier: Development Status :: 4 - Beta
Classifier: Intended Audience :: Developers
Classifier: License :: OSI Approved :: GNU General Public License v3 or later (GPLv3+)
Classifier: Programming Language :: Python :: 2
Classifier: Programming Language :: Python :: 2.7
Classifier: Programming Language :: Python :: 3
Classifier: Programming Language :: Python :: 3.3
Classifier: Programming Language :: Python :: 3.4
Classifier: Programming Language :: Python :: 3.5
Classifier: Topic :: Scientific/Engineering :: Electronic Design Automation (EDA)
